{
  "generated_at_utc": "2026-03-30T06:25:27.204307+00:00",
  "built_at_utc": "2026-03-30T06:25:29.277147+00:00",
  "project_count": 3,
  "items": [
    {
      "symbol": "HYPE",
      "name": "Hyperliquid",
      "sector": "derivatives",
      "coingecko_id": "hyperliquid",
      "thesis": [
        "协议交易手续费通过 Assistance Fund 自动换成 HYPE 并销毁，形成通缩锚。",
        "若手续费收入维持高位，则买盘与销毁可抵消并压制潜在增发抛压。",
        "作为头部链上衍生品基础设施，交易深度和流动性网络效应是核心护城河。"
      ],
      "risk_flags": [
        "估值透支：FDV/MCAP 长期维持高位",
        "手续费回落：买回销毁边际减弱",
        "赛道竞争：新兴 perp DEX 抢占交易量",
        "监管风险：高杠杆衍生品政策不确定性"
      ],
      "price_usd": 38.17,
      "market_cap_usd": 9098941105,
      "fdv_usd": 36729085770,
      "volume_24h_usd": 180227278,
      "market_cap_rank": 13,
      "price_change_7d_pct": 0.07572,
      "price_change_30d_pct": 41.90636,
      "circulating_supply": 238385315.9541414,
      "max_supply": 1000000000.0,
      "fdv_to_mcap": 4.036632982470547,
      "volume_to_mcap_pct": 1.9807500226698083,
      "circulating_ratio_pct": 23.838531595414143,
      "valuation_label": "WARN",
      "liquidity_label": "LOW",
      "valuation_note": "CoinGecko",
      "valuation_proxy": null,
      "last_updated": "2026-03-30T06:24:48.348Z"
    },
    {
      "symbol": "CRCLX",
      "name": "Circle xStock",
      "sector": "stablecoin_ai_payment",
      "coingecko_id": "circle-xstock",
      "thesis": [
        "稳定币支付基础设施叠加 AI 支付叙事，具备跨场景扩张潜力。",
        "若链上支付交易量与结算活跃度持续提升，估值可获得基本面支撑。",
        "代币化证券赛道在合规推进下，具备中长期结构性增长弹性。"
      ],
      "risk_flags": [
        "监管风险：代币化证券与支付合规政策变化",
        "流动性风险：成交深度不足时波动放大",
        "叙事切换风险：AI 支付热度下降影响估值",
        "竞品风险：稳定币支付与 RWA 赛道竞争加剧"
      ],
      "price_usd": 94.21,
      "market_cap_usd": 19230690352.397457,
      "fdv_usd": 23116507221.259388,
      "volume_24h_usd": 5840372,
      "market_cap_rank": 490,
      "price_change_7d_pct": -22.47788,
      "price_change_30d_pct": 13.92545,
      "circulating_supply": 454547.7800556644,
      "max_supply": null,
      "fdv_to_mcap": 1.202063305978898,
      "volume_to_mcap_pct": 0.030370058968121706,
      "circulating_ratio_pct": null,
      "valuation_label": "OK",
      "liquidity_label": "LOW",
      "valuation_note": "US Equity CRCL (price=93.66 @ 20260327, user-provided float/diluted shares)",
      "valuation_proxy": {
        "ticker": "CRCL",
        "price_usd": 93.66,
        "price_date": "20260327",
        "shares_basic": 205324475.25515115,
        "shares_diluted": 246813017.52358946,
        "market_cap_usd": 19230690352.397457,
        "fdv_usd": 23116507221.259388,
        "cik": "0001876042",
        "source": "stooq+user_share_override"
      },
      "last_updated": "2026-03-30T06:25:23.010Z"
    },
    {
      "symbol": "BNKR",
      "name": "BankrCoin",
      "sector": "base_ai_agent",
      "coingecko_id": "bankercoin-2",
      "thesis": [
        "Base 链 AI Agent 发行与工具定位，若生态扩张将带来平台型网络效应。",
        "当前估值在同赛道中相对便宜，具备估值修复弹性。",
        "若工具端活跃用户与链上交互持续增长，代币可获得基本面支撑。"
      ],
      "risk_flags": [
        "小市值高波动：流动性不足时回撤放大",
        "叙事依赖：AI agent 热度降温会压缩估值",
        "执行风险：平台真实采用率若不及预期，估值修复失效",
        "Base 生态竞争：同类发行/工具平台分流用户"
      ],
      "price_usd": 0.00034897,
      "market_cap_usd": 34896902,
      "fdv_usd": 34896902,
      "volume_24h_usd": 2751849,
      "market_cap_rank": 564,
      "price_change_7d_pct": -12.35334,
      "price_change_30d_pct": -36.96682,
      "circulating_supply": 99999999999.99998,
      "max_supply": 100000000000.0,
      "fdv_to_mcap": 1.0,
      "volume_to_mcap_pct": 7.885654147752142,
      "circulating_ratio_pct": 99.99999999999999,
      "valuation_label": "OK",
      "liquidity_label": "NORMAL",
      "valuation_note": "CoinGecko",
      "valuation_proxy": null,
      "last_updated": "2026-03-30T06:25:23.662Z"
    }
  ],
  "trade_review": {
    "journal_updated_at_utc": "2026-03-27T04:30:00Z",
    "summary": {
      "total_trades": 0,
      "closed_trades": 0,
      "open_trades": 0,
      "win_rate_closed_pct": null,
      "avg_return_closed_pct": null,
      "avg_alpha_closed_pct": null,
      "total_pnl_usd": 0,
      "beta_definition": "优先 benchmark_symbol 对应标的最近30d涨跌幅；缺失时回退为该交易标的最近30d涨跌幅",
      "alpha_definition": "trade_return_pct - beta_30d_pct（粗归因）"
    },
    "by_tag": [],
    "trades": []
  }
}